gspread_delimited_export/__init__.py
gspread_delimited_export/cli.py
gspread_delimited_export-0.2.2.dist-info/METADATA
gspread_delimited_export-0.2.2.dist-info/WHEEL
gspread_delimited_export-0.2.2.dist-info/entry_points.txt
gspread_delimited_export-0.2.2.dist-info/RECORD
